reporter.py
python_reporter-1.0.2.dist-info/LICENSE
python_reporter-1.0.2.dist-info/METADATA
python_reporter-1.0.2.dist-info/WHEEL
python_reporter-1.0.2.dist-info/entry_points.txt
python_reporter-1.0.2.dist-info/top_level.txt
python_reporter-1.0.2.dist-info/RECORD
